{
  "0006.jpg": "Butterfly",
  "0007.jpg": "Grasshopper",
  "0008.jpg": "Ladybug",
  "0009.jpg": "Honeybee",
  "0010.jpg": "Dragonfly",
  "0011.jpg": "Seahorse",
  "0012.jpg": "Turtle",
  "0013.jpg": "Whale",
  "0014.jpg": "Dolphin",
  "0015.jpg": "Shark",
  "0016.jpg": "Penguin",
  "0017.jpg": "Mermaid",
  "0018.jpg": "Dinosaur",
  "0019.jpg": "Triceratops",
  "0020.jpg": "T Rex",
  "0021.jpg": "Puppy",
  "0022.jpg": "Cow",
  "0023.jpg": "Horse",
  "0024.jpg": "Pig",
  "0025.jpg": "Chicken",
  "0026.jpg": "Cake",
  "0027.jpg": "Ice Cream",
  "0028.jpg": "Donut",
  "0029.jpg": "Cupcake",
  "0030.jpg": "Candy",
  "0031.jpg": "Submarine",
  "0032.jpg": "Boat",
  "0033.jpg": "Truck",
  "0034.jpg": "Hot Air Balloon",
  "0035.jpg": "Airplane",
  "0036.jpg": "Hat",
  "0037.jpg": "Shoe",
  "0038.jpg": "Gloves",
  "0039.jpg": "Coat",
  "0040.jpg": "Sock",
  "0041.jpg": "Apple",
  "0042.jpg": "Grapes",
  "0043.jpg": "Strawberry",
  "0044.jpg": "Orange",
  "0045.jpg": "Banana",

  "0046.jpg": "Burger",
  "0047.jpg": "Pizza",
  "0048.jpg": "Hot Dog",
  "0049.jpg": "Fries",
  "0050.jpg": "Sandwich",
  "0051.jpg": "Corn",
  "0052.jpg": "Tomato",
  "0053.jpg": "Pumpkin",
  "0054.jpg": "Broccoli",
  "0055.jpg": "Beetroot",

  "0056.jpg": "Snake",
  "0057.jpg": "Crocodile",
  "0058.jpg": "Lizard",
  "0059.jpg": "Camel",
  "0060.jpg": "Elephant",
  "0061.jpg": "Fox",
  "0062.jpg": "Zebra",
  "0063.jpg": "Giraffe",
  "0064.jpg": "Gorilla",
  "0065.jpg": "Koala",


  "koala.jpg": "Koala",
  "ant.jpg": "Ant",
  "bear.jpg": "Bear",
  "bunny.jpg": "Bunny",
  "bus.jpg": "Bus",
  "cactus.jpg": "Cactus",
  "candy.jpg": "Candy",
  "carrot.jpg": "Carrot",
  "cherry.jpg": "Cherry",
  "duck.jpg": "Duck",
  "flower.jpg": "Flower",
  "free.jpg": "Draw something",
  "frog.jpg": "Frog",
  "icecream.jpg": "Ice Cream",
  "pear.jpg": "Pear",
  "Shapes.jpg": "Shapes",
  "shapes2.jpg": "Shapes",
  "shapes3.jpg": "Shapes",
  "ship.jpg": "Ship",
  "tiger.jpg": "Tiger",
  "train.jpg": "Train",
  "tree.jpg": "Tree"

}
